likiskwargsmeta/__init__.py
likiskwargsmeta/kwargsmeta.py
likiskwargsmeta-0.1.0.dist-info/LICENSE
likiskwargsmeta-0.1.0.dist-info/METADATA
likiskwargsmeta-0.1.0.dist-info/WHEEL
likiskwargsmeta-0.1.0.dist-info/top_level.txt
likiskwargsmeta-0.1.0.dist-info/RECORD
