Metadata-Version: 2.2
Name: likiskwargsmeta
Version: 0.1.0
Summary: This package implements a class taking keyword arguments from methods and setting them in the init function
Home-page: https://github.com/liki-mc/kwargsmeta
Author: liki-mc
Classifier: Programming Language :: Python :: 3
Classifier: License :: OSI Approved :: MIT License
Classifier: Operating System :: OS Independent
Requires-Python: >=3.6
License-File: LICENSE
